mindi/__init__.py
mindi/core.py
mindi-0.1.0.dist-info/METADATA
mindi-0.1.0.dist-info/WHEEL
mindi-0.1.0.dist-info/RECORD
