Metadata-Version: 2.1
Name: mindi
Version: 0.1.0
Summary: A minimal dependency injection framework for Python with zero dependencies. Features type-hints support, singleton caching, and both type and string-based identifiers.
License: MIT
Author: djosix
Author-email: djosicks@gmail.com
Requires-Python: >=3.11,<4.0
Classifier: License :: OSI Approved :: MIT License
Classifier: Programming Language :: Python :: 3
Classifier: Programming Language :: Python :: 3.11
Classifier: Programming Language :: Python :: 3.12
Classifier: Programming Language :: Python :: 3.13
